boilr/__init__.py
boilr/__main__.py
boilr/_version.py
boilr/app.py
boilr/argparse.py
boilr/config.py
boilr/core.py
boilr/daemon.py
boilr/helper.py
boilr/logger.py
boilr/mqtt.py
boilr/rpi_gpio.py
boilr_pv-0.1.1.dist-info/LICENSE
boilr_pv-0.1.1.dist-info/METADATA
boilr_pv-0.1.1.dist-info/WHEEL
boilr_pv-0.1.1.dist-info/entry_points.txt
boilr_pv-0.1.1.dist-info/top_level.txt
boilr_pv-0.1.1.dist-info/RECORD
