Metadata-Version: 2.1
Name: boilr-pv
Version: 0.1.1
Summary: Water boiler automation with a Fronius pv inverter on a Raspberry Pi.
Author-email: Peter Loecker <peter.loecker@live.at>
License: MIT License
Project-URL: Homepage, https://github.com/PeterBrain/boilr
Project-URL: Documentation, https://github.com/PeterBrain/boilr
Project-URL: Source, https://github.com/PeterBrain/boilr
Project-URL: Issues, https://github.com/PeterBrain/boilr/issues
Keywords: boiler,pv,photovoltaic,solar,solar-energy,fronius-solar-api,fronius,fronius-inverter,ohmpilot,waterheater,raspberry-pi,raspberrypi
Classifier: Development Status :: 3 - Alpha
Classifier: Environment :: Console
Classifier: Intended Audience :: Developers
Classifier: License :: OSI Approved :: MIT License
Classifier: Natural Language :: English
Classifier: Natural Language :: German
Classifier: Operating System :: POSIX :: Linux
Classifier: Programming Language :: Python
Classifier: Topic :: Home Automation
Classifier: Topic :: Software Development
Classifier: Topic :: System :: Hardware
Requires-Python: <3.11,>=3.8
License-File: LICENSE
Requires-Dist: paho-mqtt
Requires-Dist: python-daemon
Requires-Dist: PyYAML
Requires-Dist: requests
Requires-Dist: urllib3
Requires-Dist: RPi.GPIO ; platform_system == "Linux" and "arm" in platform_machine
Provides-Extra: dev
Requires-Dist: pytest ; extra == 'dev'
Requires-Dist: pytest-cov ; extra == 'dev'
Requires-Dist: pytest-mock ; extra == 'dev'
